ugbib_divers/__init__.py
ugbib_divers/bibGlobal.py
ugbib_divers/bibSymbols.py
ugbib_divers-0.1.0.dist-info/METADATA
ugbib_divers-0.1.0.dist-info/WHEEL
ugbib_divers-0.1.0.dist-info/licenses/LICENSE
ugbib_divers-0.1.0.dist-info/licenses/LICENSE~
ugbib_divers-0.1.0.dist-info/RECORD
