Metadata-Version: 2.3
Name: ugbib_divers
Version: 0.1.0
Summary: Diverse Module ohne weitere Abhängigkeiten
Classifier: Programming Language :: Python :: 3
Classifier: Programming Language :: Python :: 3.10
Requires-Python: >=3.10
